tornado_swagger/__init__.py
tornado_swagger/_builders.py
tornado_swagger/_handlers.py
tornado_swagger/const.py
tornado_swagger/model.py
tornado_swagger/parameter.py
tornado_swagger/setup.py
tornado_swagger/swagger_ui/ui.html
tornado_swagger/templates/swagger.yaml
tornado_swagger-1.4.5.dist-info/LICENSE
tornado_swagger-1.4.5.dist-info/METADATA
tornado_swagger-1.4.5.dist-info/WHEEL
tornado_swagger-1.4.5.dist-info/top_level.txt
tornado_swagger-1.4.5.dist-info/RECORD
