Metadata-Version: 2.1
Name: tornado-swagger
Version: 1.4.5
Summary: Swagger API Documentation builder for tornado server
Home-page: https://github.com/mrk-andreev/tornado-swagger
Download-URL: https://pypi.org/project/tornado-swagger/#files
Author: Mark Andreev
Author-email: mark.andreev@gmail.com
License: MIT License
Classifier: Intended Audience :: System Administrators
Classifier: License :: OSI Approved :: MIT License
Classifier: Operating System :: OS Independent
Classifier: Programming Language :: Python
Classifier: Programming Language :: Python :: 3.5
Classifier: Programming Language :: Python :: 3.6
Classifier: Programming Language :: Python :: 3.7
Classifier: Programming Language :: Python :: 3.8
Classifier: Programming Language :: Python :: 3.9
Classifier: Programming Language :: Python :: 3.10
Classifier: Programming Language :: Python :: 3.11
Classifier: Topic :: Software Development :: Libraries :: Python Modules
License-File: LICENSE
Requires-Dist: tornado (>=5.0)
Requires-Dist: PyYAML (>=5.4)
